Workbook

Sheet Pruebas de aceptación
A1: N° | B1: Sección del documento | C1: Requisito (texto del documento) | D1: Caso de prueba | E1: Datos de entrada | F1: Resultado esperado | G1: Evidencia | H1: ¿Ejecutado? | I1: Resultado obtenido | J1: ¿Aprobado? | K1: Fecha | L1: Responsable
A2: 1 | B2: Anexo 1 - Equivalencias de frecuencia de pago | C2: Frecuencia 1 -> MONTHLY (Estándar): 'Cada 1 Mes(es) se realiza un pago' / 'Cada pago se divide por 1 periodo(s) por rango de fecha' | D2: Línea de pago con frecuencia estándar MONTHLY | E2: Frecuencia FLA = MONTHLY, Attribute_number_1_l = 1, Start Date y End Date informados | F2: Un solo pago en FLA con frecuencia MONTHLY, rango de fechas de la línea y Attribute Number 1 = 1. | G2: Reporte BIP + CSV Payments + contrato en FLA | H2: No
A3: 2 | B3: Anexo 1 - Equivalencias de frecuencia de pago | C3: Frecuencia 3 -> QUARTERLY (Estándar): 'Cada 3 Mes(es) se realiza un pago' / 'Cada pago se divide por 3 periodo(s) por rango de fecha' | D3: Línea de pago con frecuencia estándar QUARTERLY | E3: Frecuencia FLA = QUARTERLY, Attribute_number_1_l = 3, Start Date y End Date informados | F3: Un solo pago en FLA con frecuencia QUARTERLY, rango de fechas de la línea y Attribute Number 1 = 3. | G3: Reporte BIP + CSV Payments + contrato en FLA | H3: No
A4: 3 | B4: Anexo 1 - Equivalencias de frecuencia de pago | C4: Frecuencia 6 -> SEMI_ANNUALLY (Estándar): 'Cada 6 Mes(es) se realiza un pago' / 'Cada pago se divide por 6 periodo(s) por rango de fecha' | D4: Línea de pago con frecuencia estándar SEMI_ANNUALLY | E4: Frecuencia FLA = SEMI_ANNUALLY, Attribute_number_1_l = 6, Start Date y End Date informados | F4: Un solo pago en FLA con frecuencia SEMI_ANNUALLY, rango de fechas de la línea y Attribute Number 1 = 6. | G4: Reporte BIP + CSV Payments + contrato en FLA | H4: No
A5: 4 | B5: Anexo 1 - Equivalencias de frecuencia de pago | C5: Frecuencia 12 -> ANNUALLY (Estándar): 'Cada 12 Mes(es) se realiza un pago' / 'Cada pago se divide por 12 periodo(s) por rango de fecha' | D5: Línea de pago con frecuencia estándar ANNUALLY | E5: Frecuencia FLA = ANNUALLY, Attribute_number_1_l = 12, Start Date y End Date informados | F5: Un solo pago en FLA con frecuencia ANNUALLY, rango de fechas de la línea y Attribute Number 1 = 12. | G5: Reporte BIP + CSV Payments + contrato en FLA | H5: No
A6: 5 | B6: Anexo 1 - Equivalencias de frecuencia de pago | C6: Frecuencia 2 -> ONE_TIME (solución alternativa): 'Cada 2 Meses se realiza un pago' / 'Cada pago se divide por 2 periodos' | D6: Apertura de línea ONE_TIME con frecuencia 2 meses | E6: Frecuencia FLA = ONE_TIME, Attribute_number_1_l = 2, plazo de la línea que contenga al menos 2 periodos de 2 meses | F6: El reporte BI Publisher abre la línea en un pago ONE_TIME cada 2 meses dentro del plazo; cada pago con el monto de la línea y Attribute Number 1 = 2. FLA crea el contrato con todos los pagos. | G6: Reporte BIP + CSV Payments + calendario de pagos en FLA | H6: No
A7: 6 | B7: Anexo 1 - Equivalencias de frecuencia de pago | C7: Frecuencia 4 -> ONE_TIME (solución alternativa): 'Cada 4 Meses se realiza un pago' / 'Cada pago se divide por 4 periodos' | D7: Apertura de línea ONE_TIME con frecuencia 4 meses | E7: Frecuencia FLA = ONE_TIME, Attribute_number_1_l = 4, plazo de la línea que contenga al menos 2 periodos de 4 meses | F7: El reporte BI Publisher abre la línea en un pago ONE_TIME cada 4 meses dentro del plazo; cada pago con el monto de la línea y Attribute Number 1 = 4. FLA crea el contrato con todos los pagos. | G7: Reporte BIP + CSV Payments + calendario de pagos en FLA | H7: No
A8: 7 | B8: Anexo 1 - Equivalencias de frecuencia de pago | C8: Frecuencia 24 -> ONE_TIME (solución alternativa): 'Cada 24 Meses se realiza un pago' / 'Cada pago se divide por 24 periodos' | D8: Apertura de línea ONE_TIME con frecuencia 24 meses | E8: Frecuencia FLA = ONE_TIME, Attribute_number_1_l = 24, plazo de la línea que contenga al menos 2 periodos de 24 meses | F8: El reporte BI Publisher abre la línea en un pago ONE_TIME cada 24 meses dentro del plazo; cada pago con el monto de la línea y Attribute Number 1 = 24. FLA crea el contrato con todos los pagos. | G8: Reporte BIP + CSV Payments + calendario de pagos en FLA | H8: No
A9: 8 | B9: Anexo 1 - Equivalencias de frecuencia de pago | C9: Frecuencia 120 -> ONE_TIME (solución alternativa): 'Cada 120 Meses se realiza un pago' / 'Cada pago se divide por 120 periodos' | D9: Apertura de línea ONE_TIME con frecuencia 120 meses | E9: Frecuencia FLA = ONE_TIME, Attribute_number_1_l = 120, plazo de la línea que contenga al menos 2 periodos de 120 meses | F9: El reporte BI Publisher abre la línea en un pago ONE_TIME cada 120 meses dentro del plazo; cada pago con el monto de la línea y Attribute Number 1 = 120. FLA crea el contrato con todos los pagos. | G9: Reporte BIP + CSV Payments + calendario de pagos en FLA | H9: No
A10: 9 | B10: Anexo 1 - Equivalencias de frecuencia de pago | C10: 'La integración (OIC) consumirá el reporte con la Frecuencia de pago FLA entregada por Unifier' | D10: Frecuencia FLA entregada por Unifier | E10: Request de Unifier con el campo Frecuencia informado | F10: OIC usa la Frecuencia FLA enviada por Unifier para la apertura. | G10: Activity Stream OIC | H10: No
A11: 10 | B11: Anexo 1 - Equivalencias de frecuencia de pago | C11: 'Esta apertura … se llevará a cabo mediante un reporte BI Publisher … y traspasarlos a la estructura FBDI' | D11: Apertura ejecutada por BI Publisher | E11: Línea ONE_TIME | F11: La apertura la realiza el reporte BI Publisher (no lógica en OIC) y su salida se traspasa a la hoja Payments del FBDI. | G11: Activity Stream OIC (invocación BIP) + CSV Payments | H11: No
A12: 11 | B12: Anexo 2 - Apertura de contratos | C12: Unifier abre el contrato según Nombre de la parte (Arrendador), Moneda y Tasa de descuento; cada combinación se presenta como contrato separado | D12: Contrato Unifier con más de una combinación arrendador / moneda / tasa | E12: Contrato en Unifier con 2 combinaciones (p. ej. 2 monedas) | F12: Llegan como contratos separados en el reporte y FLA crea un contrato por combinación. | G12: Request Unifier + contratos en FLA | H12: No
A13: 12 | B13: Anexo 2 - Apertura de contratos | C13: 'La forma de diferenciarlos será a través del número de contrato … concatenará el Nro de contrato original (Unifier), junto con los atributos acordados' | D13: Número de contrato concatenado | E13: Caso anterior | F13: Cada contrato en FLA tiene Lease Number = Nro contrato Unifier concatenado con los atributos acordados; son únicos. | G13: Contratos en FLA | H13: No
... A51: 50 | B51: Mensajería y notificaciones | C51: Trazabilidad de punta a punta, desde la recepción en OIC hasta la creación o rechazo del contrato en FLA | D51: Trazabilidad de punta a punta | E51: Un contrato creado y uno rechazado | F51: Se puede seguir cada contrato desde la recepción en OIC hasta su creación o rechazo en FLA. | G51: Notificaciones + reportes | H51: No

Sheet Resumen
A1: Pruebas de aceptación - INT-0290 Creación de Contratos INBOUND
A3: Sección del documento | B3: Casos | C3: Ejecutados | D3: Aprobados | E3: % aprobado
A4: Anexo 1 - Equivalencias de frecuencia de pago | B4: =COUNTIF('Pruebas de aceptación'!$B$2:$B$51,A4) -> 10 | C4: =COUNTIFS('Pruebas de aceptación'!$B$2:$B$51,A4,'Pruebas de aceptación'!$H$2:$H$51,"Sí") -> 0 | D4: =COUNTIFS('Pruebas de aceptación'!$B$2:$B$51,A4,'Pruebas de aceptación'!$J$2:$J$51,"Sí") -> 0 | E4: =IF(B4=0,0,D4/B4) -> 0
A5: Anexo 2 - Apertura de contratos | B5: =COUNTIF('Pruebas de aceptación'!$B$2:$B$51,A5) -> 3 | C5: =COUNTIFS('Pruebas de aceptación'!$B$2:$B$51,A5,'Pruebas de aceptación'!$H$2:$H$51,"Sí") -> 0 | D5: =COUNTIFS('Pruebas de aceptación'!$B$2:$B$51,A5,'Pruebas de aceptación'!$J$2:$J$51,"Sí") -> 0 | E5: =IF(B5=0,0,D5/B5) -> 0
A6: Anexo 3 - Manejo del gasto correctivo | B6: =COUNTIF('Pruebas de aceptación'!$B$2:$B$51,A6) -> 5 | C6: =COUNTIFS('Pruebas de aceptación'!$B$2:$B$51,A6,'Pruebas de aceptación'!$H$2:$H$51,"Sí") -> 0 | D6: =COUNTIFS('Pruebas de aceptación'!$B$2:$B$51,A6,'Pruebas de aceptación'!$J$2:$J$51,"Sí") -> 0 | E6: =IF(B6=0,0,D6/B6) -> 0
A7: Escenario A: Carga masiva exitosa | B7: =COUNTIF('Pruebas de aceptación'!$B$2:$B$51,A7) -> 1 | C7: =COUNTIFS('Pruebas de aceptación'!$B$2:$B$51,A7,'Pruebas de aceptación'!$H$2:$H$51,"Sí") -> 0 | D7: =COUNTIFS('Pruebas de aceptación'!$B$2:$B$51,A7,'Pruebas de aceptación'!$J$2:$J$51,"Sí") -> 0 | E7: =IF(B7=0,0,D7/B7) -> 0
A8: Escenario B: Carga con errores | B8: =COUNTIF('Pruebas de aceptación'!$B$2:$B$51,A8) -> 2 | C8: =COUNTIFS('Pruebas de aceptación'!$B$2:$B$51,A8,'Pruebas de aceptación'!$H$2:$H$51,"Sí") -> 0 | D8: =COUNTIFS('Pruebas de aceptación'!$B$2:$B$51,A8,'Pruebas de aceptación'!$J$2:$J$51,"Sí") -> 0 | E8: =IF(B8=0,0,D8/B8) -> 0
A9: Escenario C: Reprocesamiento y ejecución manual | B9: =COUNTIF('Pruebas de aceptación'!$B$2:$B$51,A9) -> 1 | C9: =COUNTIFS('Pruebas de aceptación'!$B$2:$B$51,A9,'Pruebas de aceptación'!$H$2:$H$51,"Sí") -> 0 | D9: =COUNTIFS('Pruebas de aceptación'!$B$2:$B$51,A9,'Pruebas de aceptación'!$J$2:$J$51,"Sí") -> 0 | E9: =IF(B9=0,0,D9/B9) -> 0
A10: Carga del archivo | B10: =COUNTIF('Pruebas de aceptación'!$B$2:$B$51,A10) -> 3 | C10: =COUNTIFS('Pruebas de aceptación'!$B$2:$B$51,A10,'Pruebas de aceptación'!$H$2:$H$51,"Sí") -> 0 | D10: =COUNTIFS('Pruebas de aceptación'!$B$2:$B$51,A10,'Pruebas de aceptación'!$J$2:$J$51,"Sí") -> 0 | E10: =IF(B10=0,0,D10/B10) -> 0
A11: Procesamiento de importación | B11: =COUNTIF('Pruebas de aceptación'!$B$2:$B$51,A11) -> 5 | C11: =COUNTIFS('Pruebas de aceptación'!$B$2:$B$51,A11,'Pruebas de aceptación'!$H$2:$H$51,"Sí") -> 0 | D11: =COUNTIFS('Pruebas de aceptación'!$B$2:$B$51,A11,'Pruebas de aceptación'!$J$2:$J$51,"Sí") -> 0 | E11: =IF(B11=0,0,D11/B11) -> 0
A12: Generación de datos | B12: =COUNTIF('Pruebas de aceptación'!$B$2:$B$51,A12) -> 3 | C12: =COUNTIFS('Pruebas de aceptación'!$B$2:$B$51,A12,'Pruebas de aceptación'!$H$2:$H$51,"Sí") -> 0 | D12: =COUNTIFS('Pruebas de aceptación'!$B$2:$B$51,A12,'Pruebas de aceptación'!$J$2:$J$51,"Sí") -> 0 | E12: =IF(B12=0,0,D12/B12) -> 0
A13: Validación de datos | B13: =COUNTIF('Pruebas de aceptación'!$B$2:$B$51,A13) -> 6 | C13: =COUNTIFS('Pruebas de aceptación'!$B$2:$B$51,A13,'Pruebas de aceptación'!$H$2:$H$51,"Sí") -> 0 | D13: =COUNTIFS('Pruebas de aceptación'!$B$2:$B$51,A13,'Pruebas de aceptación'!$J$2:$J$51,"Sí") -> 0 | E13: =IF(B13=0,0,D13/B13) -> 0
A14: Datos requeridos | B14: =COUNTIF('Pruebas de aceptación'!$B$2:$B$51,A14) -> 3 | C14: =COUNTIFS('Pruebas de aceptación'!$B$2:$B$51,A14,'Pruebas de aceptación'!$H$2:$H$51,"Sí") -> 0 | D14: =COUNTIFS('Pruebas de aceptación'!$B$2:$B$51,A14,'Pruebas de aceptación'!$J$2:$J$51,"Sí") -> 0 | E14: =IF(B14=0,0,D14/B14) -> 0
A15: Alcance | B15: =COUNTIF('Pruebas de aceptación'!$B$2:$B$51,A15) -> 1 | C15: =COUNTIFS('Pruebas de aceptación'!$B$2:$B$51,A15,'Pruebas de aceptación'!$H$2:$H$51,"Sí") -> 0 | D15: =COUNTIFS('Pruebas de aceptación'!$B$2:$B$51,A15,'Pruebas de aceptación'!$J$2:$J$51,"Sí") -> 0 | E15: =IF(B15=0,0,D15/B15) -> 0
... A17: Mensajería y notificaciones | B17: =COUNTIF('Pruebas de aceptación'!$B$2:$B$51,A17) -> 4 | C17: =COUNTIFS('Pruebas de aceptación'!$B$2:$B$51,A17,'Pruebas de aceptación'!$H$2:$H$51,"Sí") -> 0 | D17: =COUNTIFS('Pruebas de aceptación'!$B$2:$B$51,A17,'Pruebas de aceptación'!$J$2:$J$51,"Sí") -> 0 | E17: =IF(B17=0,0,D17/B17) -> 0
A18: TOTAL | B18: =SUM(B4:B17) -> 50 | C18: =SUM(C4:C17) -> 0 | D18: =SUM(D4:D17) -> 0 | E18: =IF(B18=0,0,D18/B18) -> 0
A19: Integración aceptada | B19: =IF(D18=B18,"SÍ","NO") -> NO
A21: Criterio: la integración se acepta cuando todos los casos tienen ¿Aprobado? = Sí.
A22: Completar solo las columnas amarillas de la hoja 'Pruebas de aceptación'. Ejemplo de llenado: ¿Ejecutado? = Sí | Resultado obtenido = 'Contrato CLP-ST-CL-000XX7 creado con 6 pagos' | ¿Aprobado? = Sí | Fecha = 15/10/2026 | Responsable = nombre.
A23: Fuente: LS_INT-0290_ATR_LA_Unifier_Creación_Contratos_INBOUND_v3.1. Cada caso cita la sección y el texto del requisito.
